README.txt
flask_olinauth.py
setup.py
Flask_OlinAuth.egg-info/PKG-INFO
Flask_OlinAuth.egg-info/SOURCES.txt
Flask_OlinAuth.egg-info/dependency_links.txt
Flask_OlinAuth.egg-info/not-zip-safe
Flask_OlinAuth.egg-info/requires.txt
Flask_OlinAuth.egg-info/top_level.txt