Metadata-Version: 1.0
Name: Flask-OlinAuth
Version: 1.0
Summary: A simple Flask extension implementing Olin's authentication
Home-page: https://github.com/wcdolphin/flask-olinauth
Author: Cory Dolphin
Author-email: wcdolphin@gmail.com
License: MIT
Platform: any
Classifier: Environment :: Web Environment
Classifier: Intended Audience :: Developers
Classifier: License :: OSI Approved :: BSD License
Classifier: Operating System :: OS Independent
Classifier: Programming Language :: Python
Classifier: Topic :: Internet :: WWW/HTTP :: Dynamic Content
Classifier: Topic :: Software Development :: Libraries :: Python Modules
